decora_wifi/__init__.py
decora_wifi/base_model.py
decora_wifi/models/__init__.py
decora_wifi/models/action.py
decora_wifi/models/action_block.py
decora_wifi/models/activity.py
decora_wifi/models/activity_trigger.py
decora_wifi/models/alexa_token.py
decora_wifi/models/api_partner.py
decora_wifi/models/app.py
decora_wifi/models/area.py
decora_wifi/models/area_snapshot.py
decora_wifi/models/controller.py
decora_wifi/models/feed_item.py
decora_wifi/models/geocoder.py
decora_wifi/models/holiday_definition.py
decora_wifi/models/ifttt.py
decora_wifi/models/installation.py
decora_wifi/models/invitation.py
decora_wifi/models/iot_switch.py
decora_wifi/models/load.py
decora_wifi/models/load_definition.py
decora_wifi/models/load_snapshot.py
decora_wifi/models/location.py
decora_wifi/models/loop_back_auth.py
decora_wifi/models/management_tier.py
decora_wifi/models/oauth_token.py
decora_wifi/models/omni_notifier.py
decora_wifi/models/omni_notifier_email.py
decora_wifi/models/organization.py
decora_wifi/models/permission.py
decora_wifi/models/person.py
decora_wifi/models/preference.py
decora_wifi/models/residence.py
decora_wifi/models/residential_account.py
decora_wifi/models/residential_action.py
decora_wifi/models/residential_activity.py
decora_wifi/models/residential_area.py
decora_wifi/models/residential_breaker.py
decora_wifi/models/residential_breaker_panel.py
decora_wifi/models/residential_partner.py
decora_wifi/models/residential_permission.py
decora_wifi/models/residential_room.py
decora_wifi/models/residential_scene.py
decora_wifi/models/residential_schedule.py
decora_wifi/models/sensor.py
decora_wifi/models/sensor_definition.py
decora_wifi/models/sensor_snapshot.py
decora_wifi/models/shade.py
decora_wifi/models/shade_definition.py
decora_wifi/models/thermostat.py
decora_wifi/models/thermostat_definition.py
decora_wifi/models/thermostat_snapshot.py
decora_wifi/models/touchscreen.py
decora_wifi/models/touchscreen_definition.py
decora_wifi/models/user_feedback.py
decora_wifi-1.5.dist-info/licenses/LICENSE
decora_wifi-1.5.dist-info/METADATA
decora_wifi-1.5.dist-info/WHEEL
decora_wifi-1.5.dist-info/top_level.txt
decora_wifi-1.5.dist-info/RECORD
